<?xml version="1.0" encoding="utf-8" standalone="yes" ?>
<T3locallang>
	<meta type="array">
		<description></description>
		<type>module</type>
		<csh_table></csh_table>
		<labelContext type="array">
		</labelContext>
	</meta>
	<data type="array">
		<languageKey index="default" type="array">
<label index="l_cdd_20130101">Neujahrstag</label>
<label index="l_cdd_20130106">Epiphanias</label>
<label index="l_cdd_20130113">1. Sonntag nach Epiphanias</label>
<label index="l_cdd_20130120">Letzter Sonntag nach Epiphanias</label>
<label index="l_cdd_20130127">Septuagesimae</label>
<label index="l_cdd_20130203">Sexagesimae</label>
<label index="l_cdd_20130210">Estomihi</label>
<label index="l_cdd_20130217">Invocavit</label>
<label index="l_cdd_20130224">Reminiscere</label>
<label index="l_cdd_20130303">Okuli</label>
<label index="l_cdd_20130310">Laetare</label>
<label index="l_cdd_20130317">Judika</label>
<label index="l_cdd_20130324">Palmsonntag</label>
<label index="l_cdd_20130328">Gründonnerstag</label>
<label index="l_cdd_20130329">Karfreitag</label>
<label index="l_cdd_20130331">Ostersonntag</label>
<label index="l_cdd_20130401">Ostermontag</label>
<label index="l_cdd_20130407">Quasimodogeniti</label>
<label index="l_cdd_20130414">Misericordias Domini</label>
<label index="l_cdd_20130421">Jubilate</label>
<label index="l_cdd_20130428">Cantate</label>
<label index="l_cdd_20130505">Rogate</label>
<label index="l_cdd_20130509">Christi Himmelfahrt</label>
<label index="l_cdd_20130512">Exaudi</label>
<label index="l_cdd_20130519">Pfingstsonntag</label>
<label index="l_cdd_20130520">Pfingstmontag</label>
<label index="l_cdd_20130526">Trinitatis</label>
<label index="l_cdd_20130602">1. Sonntag nach Trinitatis</label>
<label index="l_cdd_20130609">2. Sonntag nach Trinitatis</label>
<label index="l_cdd_20130616">3. Sonntag nach Trinitatis</label>
<label index="l_cdd_20130623">4. Sonntag nach Trinitatis</label>
<label index="l_cdd_20130624">Johannistag</label>
<label index="l_cdd_20130630">5. Sonntag nach Trinitatis</label>
<label index="l_cdd_20130707">6. Sonntag nach Trinitatis</label>
<label index="l_cdd_20130714">7. Sonntag nach Trinitatis</label>
<label index="l_cdd_20130721">8. Sonntag nach Trinitatis</label>
<label index="l_cdd_20130728">9. Sonntag nach Trinitatis</label>
<label index="l_cdd_20130804">10. Sonntag nach Trinitatis</label>
<label index="l_cdd_20130811">11. Sonntag nach Trinitatis</label>
<label index="l_cdd_20130818">12. Sonntag nach Trinitatis</label>
<label index="l_cdd_20130825">13. Sonntag nach Trinitatis</label>
<label index="l_cdd_20130901">14. Sonntag nach Trinitatis</label>
<label index="l_cdd_20130908">15. Sonntag nach Trinitatis</label>
<label index="l_cdd_20130915">16. Sonntag nach Trinitatis</label>
<label index="l_cdd_20130922">17. Sonntag nach Trinitatis</label>
<label index="l_cdd_20130929">18. Sonntag nach Trinitatis</label>
<label index="l_cdd_20131006">Erntedank</label>
<label index="l_cdd_20131006">19. Sonntag nach Trinitatis</label>
<label index="l_cdd_20131013">20. Sonntag nach Trinitatis</label>
<label index="l_cdd_20131020">21. Sonntag nach Trinitatis</label>
<label index="l_cdd_20131027">22. Sonntag nach Trinitatis</label>
<label index="l_cdd_20131031">Reformationstag</label>
<label index="l_cdd_20131103">23. Sonntag nach Trinitatis</label>
<label index="l_cdd_20131110">Drittletzte Sonntag des Kirchenjahres</label>
<label index="l_cdd_20131117">Vorletzter Sonntag des Kirchenjahres</label>
<label index="l_cdd_20131120">Buß- und Bettag</label>
<label index="l_cdd_20131124">Ewigkeitssonntag</label>
<label index="l_cdd_20131201">1. Advent</label>
<label index="l_cdd_20131208">2. Advent</label>
<label index="l_cdd_20131215">3. Advent</label>
<label index="l_cdd_20131222">4. Advent</label>
<label index="l_cdd_20131224">Heiliger Abend</label>
<label index="l_cdd_20131225">1.Weihnachtstag</label>
<label index="l_cdd_20131226">2.Weihnachtstag</label>
<label index="l_cdd_20131229">1. Sonntag nach Weihnachten</label>
<label index="l_cdd_20131231">Silvester</label>
<label index="l_cdd_20140101">Neujahrstag</label>
<label index="l_cdd_20140105">2. Sonntag nach Weihnachten</label>
<label index="l_cdd_20140106">Epiphanias</label>
<label index="l_cdd_20140112">1. Sonntag nach Epiphanias</label>
<label index="l_cdd_20140119">2. Sonntag nach Epiphanias</label>
<label index="l_cdd_20140126">3. Sonntag nach Epiphanias</label>
<label index="l_cdd_20140202">4. Sonntag nach Epiphanias</label>
<label index="l_cdd_20140209">Letzter Sonntag nach Epiphanias</label>
<label index="l_cdd_20140216">Septuagesimae</label>
<label index="l_cdd_20140223">Sexagesimae</label>
<label index="l_cdd_20140302">Estomihi</label>
<label index="l_cdd_20140309">Invocavit</label>
<label index="l_cdd_20140316">Reminiscere</label>
<label index="l_cdd_20140323">Okuli</label>
<label index="l_cdd_20140330">Laetare</label>
<label index="l_cdd_20140406">Judika</label>
<label index="l_cdd_20140413">Palmsonntag</label>
<label index="l_cdd_20140417">Gründonnerstag</label>
<label index="l_cdd_20140418">Karfreitag</label>
<label index="l_cdd_20140420">Ostersonntag</label>
<label index="l_cdd_20140421">Ostermontag</label>
<label index="l_cdd_20140427">Quasimodogeniti</label>
<label index="l_cdd_20140504">Misericordias Domini</label>
<label index="l_cdd_20140511">Jubilate</label>
<label index="l_cdd_20140518">Cantate</label>
<label index="l_cdd_20140525">Rogate</label>
<label index="l_cdd_20140529">Christi Himmelfahrt</label>
<label index="l_cdd_20140601">Exaudi</label>
<label index="l_cdd_20140608">Pfingstsonntag</label>
<label index="l_cdd_20140609">Pfingstmontag</label>
<label index="l_cdd_20140615">Trinitatis</label>
<label index="l_cdd_20140622">1. Sonntag nach Trinitatis</label>
<label index="l_cdd_20140624">Johannistag</label>
<label index="l_cdd_20140629">2. Sonntag nach Trinitatis</label>
<label index="l_cdd_20140706">3. Sonntag nach Trinitatis</label>
<label index="l_cdd_20140713">4. Sonntag nach Trinitatis</label>
<label index="l_cdd_20140720">5. Sonntag nach Trinitatis</label>
<label index="l_cdd_20140727">6. Sonntag nach Trinitatis</label>
<label index="l_cdd_20140803">7. Sonntag nach Trinitatis</label>
<label index="l_cdd_20140810">8. Sonntag nach Trinitatis</label>
<label index="l_cdd_20140817">9. Sonntag nach Trinitatis</label>
<label index="l_cdd_20140824">10. Sonntag nach Trinitatis</label>
<label index="l_cdd_20140831">11. Sonntag nach Trinitatis</label>
<label index="l_cdd_20140907">12. Sonntag nach Trinitatis</label>
<label index="l_cdd_20140914">13. Sonntag nach Trinitatis</label>
<label index="l_cdd_20140921">14. Sonntag nach Trinitatis</label>
<label index="l_cdd_20140928">15. Sonntag nach Trinitatis</label>
<label index="l_cdd_20141005">16. Sonntag nach Trinitatis</label>
<label index="l_cdd_20141012">17. Sonntag nach Trinitatis</label>
<label index="l_cdd_20141019">18. Sonntag nach Trinitatis</label>
<label index="l_cdd_20141026">19. Sonntag nach Trinitatis</label>
<label index="l_cdd_20141031">Reformationstag</label>
<label index="l_cdd_20141102">20. Sonntag nach Trinitatis</label>
<label index="l_cdd_20141109">Drittletzer Sonntag des Kirchenjahres</label>
<label index="l_cdd_20141116">Vorletzter Sonntag des Kirchenjahres</label>
<label index="l_cdd_20141119">Buß- und Bettag</label>
<label index="l_cdd_20141123">Ewigkeitssonntag</label>
<label index="l_cdd_20141130">1. Advent</label>
<label index="l_cdd_20141207">2. Advent</label>
<label index="l_cdd_20141214">3. Advent</label>
<label index="l_cdd_20141221">4. Advent</label>
<label index="l_cdd_20141224">Heiliger Abend</label>
<label index="l_cdd_20141225">1.Weihnachtstag</label>
<label index="l_cdd_20141226">2.Weihnachtstag</label>
<label index="l_cdd_20141228">1. Sonntag nach Weihnachten</label>
<label index="l_cdd_20141231">Silvester</label>
<label index="l_cdd_20150101">Neujahrstag</label>
<label index="l_cdd_20150104">2. Sonntag nach Weihnachten</label>
<label index="l_cdd_20150106">Epiphanias</label>
<label index="l_cdd_20150111">1. Sonntag nach Epiphanias</label>
<label index="l_cdd_20150118">2. Sonntag nach Epiphanias</label>
<label index="l_cdd_20150125">Letzter Sonntag nach Epiphanias</label>
<label index="l_cdd_20150201">Septuagesimae</label>
<label index="l_cdd_20150208">Sexagesimae</label>
<label index="l_cdd_20150215">Estomihi</label>
<label index="l_cdd_20150222">Invocavit</label>
<label index="l_cdd_20150301">Reminiscere</label>
<label index="l_cdd_20150308">Okuli</label>
<label index="l_cdd_20150315">Laetare</label>
<label index="l_cdd_20150322">Judika</label>
<label index="l_cdd_20150329">Palmsonntag</label>
<label index="l_cdd_20150402">Gründonnerstag</label>
<label index="l_cdd_20150403">Karfreitag</label>
<label index="l_cdd_20150405">Ostersonntag</label>
<label index="l_cdd_20150406">Ostermontag</label>
<label index="l_cdd_20150412">Quasimodogeniti</label>
<label index="l_cdd_20150419">Misericordias Domini</label>
<label index="l_cdd_20150426">Jubilate</label>
<label index="l_cdd_20150503">Cantate</label>
<label index="l_cdd_20150510">Rogate</label>
<label index="l_cdd_20150514">Christi Himmelfahrt</label>
<label index="l_cdd_20150517">Exaudi</label>
<label index="l_cdd_20150524">Pfingstsonntag</label>
<label index="l_cdd_20150525">Pfingstmontag</label>
<label index="l_cdd_20150531">Trinitatis</label>
<label index="l_cdd_20150607">1. Sonntag nach Trinitatis</label>
<label index="l_cdd_20150614">2. Sonntag nach Trinitatis</label>
<label index="l_cdd_20150621">3. Sonntag nach Trinitatis</label>
<label index="l_cdd_20150624">Johannistag</label>
<label index="l_cdd_20150628">4. Sonntag nach Trinitatis</label>
<label index="l_cdd_20150705">5. Sonntag nach Trinitatis</label>
<label index="l_cdd_20150712">6. Sonntag nach Trinitatis</label>
<label index="l_cdd_20150719">7. Sonntag nach Trinitatis</label>
<label index="l_cdd_20150726">8. Sonntag nach Trinitatis</label>
<label index="l_cdd_20150802">9. Sonntag nach Trinitatis</label>
<label index="l_cdd_20150809">10. Sonntag nach Trinitatis</label>
<label index="l_cdd_20150816">11. Sonntag nach Trinitatis</label>
<label index="l_cdd_20150823">12. Sonntag nach Trinitatis</label>
<label index="l_cdd_20150830">13. Sonntag nach Trinitatis</label>
<label index="l_cdd_20150906">14. Sonntag nach Trinitatis</label>
<label index="l_cdd_20150913">15. Sonntag nach Trinitatis</label>
<label index="l_cdd_20150920">16. Sonntag nach Trinitatis</label>
<label index="l_cdd_20150927">17. Sonntag nach Trinitatis</label>
<label index="l_cdd_20151004">Erntedank</label>
<label index="l_cdd_20151004">18. Sonntag nach Trinitatis</label>
<label index="l_cdd_20151011">19. Sonntag nach Trinitatis</label>
<label index="l_cdd_20151018">20. Sonntag nach Trinitatis</label>
<label index="l_cdd_20151025">21. Sonntag nach Trinitatis</label>
<label index="l_cdd_20151031">Reformationstag</label>
<label index="l_cdd_20151101">22. Sonntag nach Trinitatis</label>
<label index="l_cdd_20151108">Drittletzer Sonntag des Kirchenjahres</label>
<label index="l_cdd_20151115">Vorletzer Sonntag des Kirchenjahres</label>
<label index="l_cdd_20151118">Buß- und Bettag</label>
<label index="l_cdd_20151122">Ewigkeitssonntag</label>
<label index="l_cdd_20151129">1. Advent</label>
<label index="l_cdd_20151206">2. Advent</label>
<label index="l_cdd_20151213">3. Advent</label>
<label index="l_cdd_20151220">4. Advent</label>
<label index="l_cdd_20151224">Heiliger Abend</label>
<label index="l_cdd_20151225">1.Weihnachtstag</label>
<label index="l_cdd_20151226">2.Weihnachtstag</label>
<label index="l_cdd_20151227">1. Sonntag nach Weihnachten</label>
<label index="l_cdd_20151231">Silvester</label>
<label index="l_cdd_20160101">Neujahrstag</label>
<label index="l_cdd_20160103">2. Sonntag nach Weihnachten</label>
<label index="l_cdd_20160106">Epiphanias</label>
<label index="l_cdd_20160110">1. Sonntag nach Epiphanias</label>
<label index="l_cdd_20160117">Letzter Sonntag nach Epiphanias</label>
<label index="l_cdd_20160124">Septuagesimae</label>
<label index="l_cdd_20160131">Sexagesimae</label>
<label index="l_cdd_20160207">Estomihi</label>
<label index="l_cdd_20160214">Invocavit</label>
<label index="l_cdd_20160221">Reminiscere</label>
<label index="l_cdd_20160228">Okuli</label>
<label index="l_cdd_20160306">Laetare</label>
<label index="l_cdd_20160313">Judika</label>
<label index="l_cdd_20160320">Palmsonntag</label>
<label index="l_cdd_20160324">Gründonnerstag</label>
<label index="l_cdd_20160325">Karfreitag</label>
<label index="l_cdd_20160327">Ostersonntag</label>
<label index="l_cdd_20160328">Ostermontag</label>
<label index="l_cdd_20160403">Quasimodogeniti</label>
<label index="l_cdd_20160410">Misericordias Domini</label>
<label index="l_cdd_20160417">Jubilate</label>
<label index="l_cdd_20160424">Cantate</label>
<label index="l_cdd_20160501">Rogate</label>
<label index="l_cdd_20160505">Christi Himmelfahrt</label>
<label index="l_cdd_20160508">Exaudi</label>
<label index="l_cdd_20160515">Pfingstsonntag</label>
<label index="l_cdd_20160516">Pfingstmontag</label>
<label index="l_cdd_20160522">Trinitatis</label>
<label index="l_cdd_20160529">1. Sonntag nach Trinitatis</label>
<label index="l_cdd_20160605">2. Sonntag nach Trinitatis</label>
<label index="l_cdd_20160612">3. Sonntag nach Trinitatis</label>
<label index="l_cdd_20160619">4. Sonntag nach Trinitatis</label>
<label index="l_cdd_20160624">Johannistag</label>
<label index="l_cdd_20160626">5. Sonntag nach Trinitatis</label>
<label index="l_cdd_20160703">6. Sonntag nach Trinitatis</label>
<label index="l_cdd_20160710">7. Sonntag nach Trinitatis</label>
<label index="l_cdd_20160717">8. Sonntag nach Trinitatis</label>
<label index="l_cdd_20160724">9. Sonntag nach Trinitatis</label>
<label index="l_cdd_20160731">10. Sonntag nach Trinitatis</label>
<label index="l_cdd_20160807">11. Sonntag nach Trinitatis</label>
<label index="l_cdd_20160814">12. Sonntag nach Trinitatis</label>
<label index="l_cdd_20160821">13. Sonntag nach Trinitatis</label>
<label index="l_cdd_20160828">14. Sonntag nach Trinitatis</label>
<label index="l_cdd_20160904">15. Sonntag nach Trinitatis</label>
<label index="l_cdd_20160911">16. Sonntag nach Trinitatis</label>
<label index="l_cdd_20160918">17. Sonntag nach Trinitatis</label>
<label index="l_cdd_20160925">18. Sonntag nach Trinitatis</label>
<label index="l_cdd_20161002">Erntedank</label>
<label index="l_cdd_20161002">19. Sonntag nach Trinitatis</label>
<label index="l_cdd_20161009">20. Sonntag nach Trinitatis</label>
<label index="l_cdd_20161016">21. Sonntag nach Trinitatis</label>
<label index="l_cdd_20161023">22. Sonntag nach Trinitatis</label>
<label index="l_cdd_20161030">23. Sonntag nach Trinitatis</label>
<label index="l_cdd_20161031">Reformationstag</label>
<label index="l_cdd_20161106">Drittletzer Sonntag des Kirchenjahres</label>
<label index="l_cdd_20161113">Vorletzter Sonntag des Kirchenjahres</label>
<label index="l_cdd_20161116">Buß- und Bettag</label>
<label index="l_cdd_20161120">Ewigkeitssonntag</label>
<label index="l_cdd_20161127">1. Advent</label>
<label index="l_cdd_20161204">2. Advent</label>
<label index="l_cdd_20161211">3. Advent</label>
<label index="l_cdd_20161218">4. Advent</label>
<label index="l_cdd_20161224">Heiligabend</label>
<label index="l_cdd_20161225">1. Weihnachtstag</label>
<label index="l_cdd_20161226">2. Weihnachtstag</label>
<label index="l_cdd_20161231">Altjahresabend / Silvester</label>
<label index="l_cdd_20170101">Neujahrstag</label>
<label index="l_cdd_20170106">Epiphanias (Erscheinungsfest)</label>
<label index="l_cdd_20170108">1. Sonntag nach Epiphanias</label>
<label index="l_cdd_20170115">2. Sonntag nach Epiphanias</label>
<label index="l_cdd_20170122">3. Sonntag nach Epiphanias</label>
<label index="l_cdd_20170129">4. Sonntag nach Epiphanias</label>
<label index="l_cdd_20170205">letzter Sonntag nach Epiphanias</label>
<label index="l_cdd_20170212">Septuagesimä</label>
<label index="l_cdd_20170219">Sexagesimä</label>
<label index="l_cdd_20170226">Estomihi</label>
<label index="l_cdd_20170301">Aschermittwoch</label>
<label index="l_cdd_20170305">Invocavit</label>
<label index="l_cdd_20170312">Reminiscere</label>
<label index="l_cdd_20170319">Okuli</label>
<label index="l_cdd_20170326">Lätare</label>
<label index="l_cdd_20170402">Judika</label>
<label index="l_cdd_20170409">Palmarum / Palmsonntag</label>
<label index="l_cdd_20170413">Gründonnerstag</label>
<label index="l_cdd_20170414">Karfreitag</label>
<label index="l_cdd_20170415">Osternacht</label>
<label index="l_cdd_20170415">Karsamstag</label>
<label index="l_cdd_20170416">Ostersonntag</label>
<label index="l_cdd_20170417">Ostermontag</label>
<label index="l_cdd_20170423">Quasimodogeniti</label>
<label index="l_cdd_20170430">Misericordias Domini</label>
<label index="l_cdd_20170507">Jubilate</label>
<label index="l_cdd_20170514">Kantate</label>
<label index="l_cdd_20170521">Rogate</label>
<label index="l_cdd_20170525">Christi Himmelfahrt</label>
<label index="l_cdd_20170528">Exaudi</label>
<label index="l_cdd_20170604">Pfingstsonntag</label>
<label index="l_cdd_20170605">Pfingstmontag</label>
<label index="l_cdd_20170611">Trinitatis</label>
<label index="l_cdd_20170618">1. Sonntag n. Trinitatis</label>
<label index="l_cdd_20170624">Tag d. Geb. Johannes d. Täufers</label>
<label index="l_cdd_20170625">2. Sonntag n. Trinitatis</label>
<label index="l_cdd_20170702">3. Sonntag n. Trinitatis</label>
<label index="l_cdd_20170709">4. Sonntag n. Trinitatis</label>
<label index="l_cdd_20170716">5. Sonntag n. Trinitatis</label>
<label index="l_cdd_20170723">6. Sonntag n. Trinitatis</label>
<label index="l_cdd_20170730">7. Sonntag n. Trinitatis</label>
<label index="l_cdd_20170806">8. Sonntag n. Trinitatis</label>
<label index="l_cdd_20170813">9. Sonntag n. Trinitatis</label>
<label index="l_cdd_20170820">10. Sonntag n. Trinitatis</label>
<label index="l_cdd_20170827">11. Sonntag n. Trinitatis</label>
<label index="l_cdd_20170903">12. Sonntag n. Trinitatis</label>
<label index="l_cdd_20170910">13. Sonntag n. Trinitatis</label>
<label index="l_cdd_20170917">14. Sonntag n. Trinitatis</label>
<label index="l_cdd_20170924">15. Sonntag n. Trinitatis</label>
<label index="l_cdd_20170929">Michaelistag</label>
<label index="l_cdd_20171001">16. Sonntag n. Trinitatis</label>
<label index="l_cdd_20171008">17. Sonntag n. Trinitatis</label>
<label index="l_cdd_20171015">18. Sonntag n. Trinitatis</label>
<label index="l_cdd_20171022">19. Sonntag n. Trinitatis</label>
<label index="l_cdd_20171029">20. Sonntag n. Trinitatis</label>
<label index="l_cdd_20171031">Reformationstag</label>
<label index="l_cdd_20171105">21. Sonntag n. Trinitatis</label>
<label index="l_cdd_20171112">Drittl.Sonntag d.Kirchenjahres</label>
<label index="l_cdd_20171119">Vorletzter Sonntag d. Kirchenjahres</label>
<label index="l_cdd_20171122">Buß-und Bettag</label>
<label index="l_cdd_20171126">Ewigkeitssonntag</label>
<label index="l_cdd_20171203">1. Advent</label>
<label index="l_cdd_20171210">2. Advent</label>
<label index="l_cdd_20171217">3. Advent</label>
<label index="l_cdd_20171224">Heiligabend</label>
<label index="l_cdd_20171224">4. Advent</label>
<label index="l_cdd_20171225">1. Weihnachtstag</label>
<label index="l_cdd_20171226">2. Weihnachtstag</label>
<label index="l_cdd_20171231">Altjahresabend / Silvester</label>
<label index="l_cdd_20180101">Neujahrstag</label>
<label index="l_cdd_20180106">Epiphanias (Erscheinungsfest)</label>
<label index="l_cdd_20180107">1. Sonntag nach Epiphanias</label>
<label index="l_cdd_20180114">2. Sonntag nach Epiphanias</label>
<label index="l_cdd_20180121">letzter Sonntag nach Epiphanias</label>
<label index="l_cdd_20180128">Septuagesimä</label>
<label index="l_cdd_20180204">Sexagesimä</label>
<label index="l_cdd_20180211">Estomihi</label>
<label index="l_cdd_20180214">Aschermittwoch</label>
<label index="l_cdd_20180218">Invocavit</label>
<label index="l_cdd_20180225">Reminiscere</label>
<label index="l_cdd_20180304">Okuli</label>
<label index="l_cdd_20180311">Lätare</label>
<label index="l_cdd_20180318">Judika</label>
<label index="l_cdd_20180325">Palmarum / Palmsonntag</label>
<label index="l_cdd_20180329">Gründonnerstag</label>
<label index="l_cdd_20180330">Karfreitag</label>
<label index="l_cdd_20180331">Karsamstag</label>
<label index="l_cdd_20180331">Osternacht</label>
<label index="l_cdd_20180401">Ostersonntag</label>
<label index="l_cdd_20180402">Ostermontag</label>
<label index="l_cdd_20180408">Quasimodogeniti</label>
<label index="l_cdd_20180415">Misericordias Domini</label>
<label index="l_cdd_20180422">Jubilate</label>
<label index="l_cdd_20180429">Kantate</label>
<label index="l_cdd_20180506">Rogate</label>
<label index="l_cdd_20180510">Christi Himmelfahrt</label>
<label index="l_cdd_20180513">Exaudi</label>
<label index="l_cdd_20180520">Pfingstsonntag</label>
<label index="l_cdd_20180521">Pfingstmontag</label>
<label index="l_cdd_20180527">Trinitatis</label>
<label index="l_cdd_20180603">1. Sonntag n. Trinitatis</label>
<label index="l_cdd_20180610">2. Sonntag n. Trinitatis</label>
<label index="l_cdd_20180617">3. Sonntag n. Trinitatis</label>
<label index="l_cdd_20180624">Tag d. Geb. Johannes d. Täufers</label>
<label index="l_cdd_20180624">4. Sonntag n. Trinitatis</label>
<label index="l_cdd_20180701">5. Sonntag n. Trinitatis</label>
<label index="l_cdd_20180708">6. Sonntag n. Trinitatis</label>
<label index="l_cdd_20180715">7. Sonntag n. Trinitatis</label>
<label index="l_cdd_20180722">8. Sonntag n. Trinitatis</label>
<label index="l_cdd_20180729">9. Sonntag n. Trinitatis</label>
<label index="l_cdd_20180805">10. Sonntag n. Trinitatis</label>
<label index="l_cdd_20180812">11. Sonntag n. Trinitatis</label>
<label index="l_cdd_20180819">12. Sonntag n. Trinitatis</label>
<label index="l_cdd_20180826">13. Sonntag n. Trinitatis</label>
<label index="l_cdd_20180902">14. Sonntag n. Trinitatis</label>
<label index="l_cdd_20180909">15. Sonntag n. Trinitatis</label>
<label index="l_cdd_20180916">16. Sonntag n. Trinitatis</label>
<label index="l_cdd_20180923">17. Sonntag n. Trinitatis</label>
<label index="l_cdd_20180929">Michaelistag</label>
<label index="l_cdd_20180930">18. Sonntag n. Trinitatis</label>
<label index="l_cdd_20181007">19. Sonntag n. Trinitatis</label>
<label index="l_cdd_20181014">20. Sonntag n. Trinitatis</label>
<label index="l_cdd_20181021">21. Sonntag n. Trinitatis</label>
<label index="l_cdd_20181028">22. Sonntag n. Trinitatis</label>
<label index="l_cdd_20181031">Reformationstag</label>
<label index="l_cdd_20181104">23. Sonntag n. Trinitatis</label>
<label index="l_cdd_20181111">Drittl.Sonntag d.Kirchenjahres</label>
<label index="l_cdd_20181118">Vorletzter Sonntag d. Kirchenjahres</label>
<label index="l_cdd_20181121">Buß-und Bettag</label>
<label index="l_cdd_20181125">Ewigkeitssonntag</label>
<label index="l_cdd_20181202">1. Advent</label>
<label index="l_cdd_20181209">2. Advent</label>
<label index="l_cdd_20181216">3. Advent</label>
<label index="l_cdd_20181223">4. Advent</label>
<label index="l_cdd_20181224">Heiligabend</label>
<label index="l_cdd_20181225">1. Weihnachtstag</label>
<label index="l_cdd_20181226">2. Weihnachtstag</label>
<label index="l_cdd_20181230">1. Sonntag n. Christfest</label>
<label index="l_cdd_20181231">Altjahresabend / Silvester</label>
<label index="l_cdd_20190101">Neujahrstag</label>
<label index="l_cdd_20190106">Epiphanias (Erscheinungsfest)</label>
<label index="l_cdd_20190113">1. Sonntag nach Epiphanias</label>
<label index="l_cdd_20190120">2. Sonntag nach Epiphanias</label>
<label index="l_cdd_20190127">3. Sonntag nach Epiphanias</label>
<label index="l_cdd_20190203">4. Sonntag nach Epiphanias</label>
<label index="l_cdd_20190210">letzter Sonntag nach Epiphanias</label>
<label index="l_cdd_20190217">Septuagesimä</label>
<label index="l_cdd_20190224">Sexagesimä</label>
<label index="l_cdd_20190303">Estomihi</label>
<label index="l_cdd_20190306">Aschermittwoch</label>
<label index="l_cdd_20190310">Invocavit</label>
<label index="l_cdd_20190317">Reminiscere</label>
<label index="l_cdd_20190324">Okuli</label>
<label index="l_cdd_20190331">Lätare</label>
<label index="l_cdd_20190407">Judika</label>
<label index="l_cdd_20190414">Palmarum / Palmsonntag</label>
<label index="l_cdd_20190418">Gründonnerstag</label>
<label index="l_cdd_20190419">Karfreitag</label>
<label index="l_cdd_20190420">Osternacht</label>
<label index="l_cdd_20190420">Karsamstag</label>
<label index="l_cdd_20190421">Ostersonntag</label>
<label index="l_cdd_20190422">Ostermontag</label>
<label index="l_cdd_20190428">Quasimodogeniti</label>
<label index="l_cdd_20190505">Misericordias Domini</label>
<label index="l_cdd_20190512">Jubilate</label>
<label index="l_cdd_20190519">Kantate</label>
<label index="l_cdd_20190526">Rogate</label>
<label index="l_cdd_20190530">Christi Himmelfahrt</label>
<label index="l_cdd_20190602">Exaudi</label>
<label index="l_cdd_20190609">Pfingstsonntag</label>
<label index="l_cdd_20190610">Pfingstmontag</label>
<label index="l_cdd_20190616">Trinitatis</label>
<label index="l_cdd_20190623">1. Sonntag n. Trinitatis</label>
<label index="l_cdd_20190624">Tag d. Geb. Johannes d. Täufers</label>
<label index="l_cdd_20190630">2. Sonntag n. Trinitatis</label>
<label index="l_cdd_20190707">3. Sonntag n. Trinitatis</label>
<label index="l_cdd_20190714">4. Sonntag n. Trinitatis</label>
<label index="l_cdd_20190721">5. Sonntag n. Trinitatis</label>
<label index="l_cdd_20190728">6. Sonntag n. Trinitatis</label>
<label index="l_cdd_20190804">7. Sonntag n. Trinitatis</label>
<label index="l_cdd_20190811">8. Sonntag n. Trinitatis</label>
<label index="l_cdd_20190818">9. Sonntag n. Trinitatis</label>
<label index="l_cdd_20190825">10. Sonntag n. Trinitatis</label>
<label index="l_cdd_20190901">11. Sonntag n. Trinitatis</label>
<label index="l_cdd_20190908">12. Sonntag n. Trinitatis</label>
<label index="l_cdd_20190915">13. Sonntag n. Trinitatis</label>
<label index="l_cdd_20190922">14. Sonntag n. Trinitatis</label>
<label index="l_cdd_20190929">15. Sonntag n. Trinitatis</label>
<label index="l_cdd_20191006">16. Sonntag n. Trinitatis</label>
<label index="l_cdd_20191013">17. Sonntag n. Trinitatis</label>
<label index="l_cdd_20191020">18. Sonntag n. Trinitatis</label>
<label index="l_cdd_20191027">19. Sonntag n. Trinitatis</label>
<label index="l_cdd_20191031">Reformationstag</label>
<label index="l_cdd_20191103">20. Sonntag n. Trinitatis</label>
<label index="l_cdd_20191110">Drittl.Sonntag d.Kirchenjahres</label>
<label index="l_cdd_20191117">Vorletzter Sonntag d. Kirchenjahres</label>
<label index="l_cdd_20191120">Buß-und Bettag</label>
<label index="l_cdd_20191124">Ewigkeitssonntag</label>
<label index="l_cdd_20191201">1. Advent</label>
<label index="l_cdd_20191208">2. Advent</label>
<label index="l_cdd_20191215">3. Advent</label>
<label index="l_cdd_20191222">4. Advent</label>
<label index="l_cdd_20191224">Heiligabend</label>
<label index="l_cdd_20191225">1. Weihnachtstag</label>
<label index="l_cdd_20191226">2. Weihnachtstag</label>
<label index="l_cdd_20191229">1. Sonntag n. Christfest</label>
<label index="l_cdd_20191231">Altjahresabend / Silvester</label>
<label index="l_cdd_20200101">Neujahrstag</label>
<label index="l_cdd_20200105">2. Sonntag nach Christfest</label>
<label index="l_cdd_20200106">Epiphanias (Erscheinungsfest)</label>
<label index="l_cdd_20200112">1. Sonntag nach Epiphanias</label>
<label index="l_cdd_20200119">2. Sonntag nach Epiphanias</label>
<label index="l_cdd_20200126">3. Sonntag nach Epiphanias</label>
<label index="l_cdd_20200202">letzter Sonntag nach Epiphanias</label>
<label index="l_cdd_20200209">Septuagesimä</label>
<label index="l_cdd_20200216">Sexagesimä</label>
<label index="l_cdd_20200223">Estomihi</label>
<label index="l_cdd_20200226">Aschermittwoch</label>
<label index="l_cdd_20200301">Invocavit</label>
<label index="l_cdd_20200308">Reminiscere</label>
<label index="l_cdd_20200315">Okuli</label>
<label index="l_cdd_20200322">Lätare</label>
<label index="l_cdd_20200329">Judika</label>
<label index="l_cdd_20200405">Palmarum / Palmsonntag</label>
<label index="l_cdd_20200409">Gründonnerstag</label>
<label index="l_cdd_20200410">Karfreitag</label>
<label index="l_cdd_20200411">Karsamstag</label>
<label index="l_cdd_20200411">Osternacht</label>
<label index="l_cdd_20200412">Ostersonntag</label>
<label index="l_cdd_20200413">Ostermontag</label>
<label index="l_cdd_20200419">Quasimodogeniti</label>
<label index="l_cdd_20200426">Misericordias Domini</label>
<label index="l_cdd_20200503">Jubilate</label>
<label index="l_cdd_20200510">Kantate</label>
<label index="l_cdd_20200517">Rogate</label>
<label index="l_cdd_20200521">Christi Himmelfahrt</label>
<label index="l_cdd_20200524">Exaudi</label>
<label index="l_cdd_20200531">Pfingstsonntag</label>
<label index="l_cdd_20200601">Pfingstmontag</label>
<label index="l_cdd_20200607">Trinitatis</label>
<label index="l_cdd_20200614">1. Sonntag n. Trinitatis</label>
<label index="l_cdd_20200621">2. Sonntag n. Trinitatis</label>
<label index="l_cdd_20200624">Tag d. Geb. Johannes d. Täufers</label>
<label index="l_cdd_20200628">3. Sonntag n. Trinitatis</label>
<label index="l_cdd_20200705">4. Sonntag n. Trinitatis</label>
<label index="l_cdd_20200712">5. Sonntag n. Trinitatis</label>
<label index="l_cdd_20200719">6. Sonntag n. Trinitatis</label>
<label index="l_cdd_20200726">7. Sonntag n. Trinitatis</label>
<label index="l_cdd_20200802">8. Sonntag n. Trinitatis</label>
<label index="l_cdd_20200809">9. Sonntag n. Trinitatis</label>
<label index="l_cdd_20200816">10. Sonntag n. Trinitatis</label>
<label index="l_cdd_20200823">11. Sonntag n. Trinitatis</label>
<label index="l_cdd_20200830">12. Sonntag n. Trinitatis</label>
<label index="l_cdd_20200906">13. Sonntag n. Trinitatis</label>
<label index="l_cdd_20200913">14. Sonntag n. Trinitatis</label>
<label index="l_cdd_20200920">15. Sonntag n. Trinitatis</label>
<label index="l_cdd_20200927">16. Sonntag n. Trinitatis</label>
<label index="l_cdd_20200929">Michaelistag</label>
<label index="l_cdd_20201004">17. Sonntag n. Trinitatis</label>
<label index="l_cdd_20201011">18. Sonntag n. Trinitatis</label>
<label index="l_cdd_20201018">19. Sonntag n. Trinitatis</label>
<label index="l_cdd_20201025">20. Sonntag n. Trinitatis</label>
<label index="l_cdd_20201031">Reformationstag</label>
<label index="l_cdd_20201101">21. Sonntag n. Trinitatis</label>
<label index="l_cdd_20201108">Drittl.Sonntag d.Kirchenjahres</label>
<label index="l_cdd_20201115">Vorletzter Sonntag d. Kirchenjahres</label>
<label index="l_cdd_20201118">Buß-und Bettag</label>
<label index="l_cdd_20201122">Ewigkeitssonntag</label>
		</languageKey>
	</data>
	<orig_hash type="array">
		<languageKey index="default" type="array">
		
		</languageKey>
	</orig_hash>
</T3locallang>